python_cueclient-1.0.0.dist-info/pbr.json
python_cueclient-1.0.0.dist-info/metadata.json
python_cueclient-1.0.0.dist-info/entry_points.txt
python_cueclient-1.0.0.dist-info/top_level.txt
python_cueclient-1.0.0.dist-info/WHEEL
python_cueclient-1.0.0.dist-info/METADATA
python_cueclient-1.0.0.dist-info/DESCRIPTION.rst
python_cueclient-1.0.0.dist-info/RECORD
cueclient/version.py
cueclient/warlock.py
cueclient/utils.py
cueclient/controller.py
cueclient/__init__.py
cueclient/tests/base.py
cueclient/tests/fixture_data.py
cueclient/tests/__init__.py
cueclient/tests/unit/__init__.py
cueclient/tests/unit/v1/test_clusters.py
cueclient/tests/unit/v1/__init__.py
cueclient/osc/plugin.py
cueclient/osc/__init__.py
cueclient/resources/schemas/v1/cluster.json
cueclient/v1/client.py
cueclient/v1/__init__.py
cueclient/v1/clusters.py
cueclient/v1/cli/__init__.py
cueclient/v1/cli/clusters.py
