Metadata-Version: 2.0
Name: python-cueclient
Version: 1.0.0
Summary: Message Broker Provisioning Service Cue Client
Home-page: http://www.openstack.org/
Author: OpenStack
Author-email: openstack-dev@lists.openstack.org
License: Apache License, Version 2.0
Platform: UNKNOWN
Classifier: Environment :: OpenStack
Classifier: Intended Audience :: Information Technology
Classifier: Intended Audience :: System Administrators
Classifier: License :: OSI Approved :: Apache Software License
Classifier: Operating System :: POSIX :: Linux
Classifier: Programming Language :: Python
Classifier: Programming Language :: Python :: 2
Classifier: Programming Language :: Python :: 2.7
Requires-Dist: cliff (>=1.14.0)
Requires-Dist: jsonschema (!=2.5.0,<3.0.0,>=2.0.0)
Requires-Dist: pbr (>=1.6)
Requires-Dist: python-keystoneclient (>=1.6.0)
Requires-Dist: requests (>=2.5.2)
Requires-Dist: six (>=1.9.0)
Requires-Dist: stevedore (>=1.5.0)
